SelfHealing/SelfHealing.py
SelfHealing/__init__.py
SelfHealing/appium_healing.py
SelfHealing/browser_healing.py
SelfHealing/llm_client.py
SelfHealing/locator_db.py
SelfHealing/selenium_healing.py
SelfHealing/template_new.html
SelfHealing/update_locators.py
SelfHealing/utils.py
SelfHealing/visual_healing.py
smart_selfhealing_rbfw-0.1.2.dist-info/METADATA
smart_selfhealing_rbfw-0.1.2.dist-info/WHEEL
smart_selfhealing_rbfw-0.1.2.dist-info/licenses/LICENSE
smart_selfhealing_rbfw-0.1.2.dist-info/RECORD
