Metadata-Version: 2.4
Name: smart-selfhealing-rbfw
Version: 0.1.2
Summary: Self-healing test automation library for Robot Framework with AI-powered locator fixing
License: Apache-2.0
License-File: LICENSE
Keywords: robotframework,testing,self-healing,automation,selenium,playwright,ai,llm,test-automation,locator-healing
Author: Hieu La
Author-email: hieuld@smartosc.com
Maintainer: Hieu La
Maintainer-email: hieuld@smartosc.com
Requires-Python: >=3.10,<4.0
Classifier: Development Status :: 4 - Beta
Classifier: Framework :: Robot Framework
Classifier: Framework :: Robot Framework :: Library
Classifier: Intended Audience :: Developers
Classifier: License :: OSI Approved :: Apache Software License
Classifier: Operating System :: OS Independent
Classifier: Programming Language :: Python :: 3
Classifier: Programming Language :: Python :: 3.10
Classifier: Programming Language :: Python :: 3.11
Classifier: Programming Language :: Python :: 3.12
Classifier: Programming Language :: Python :: 3.13
Classifier: Programming Language :: Python :: 3.14
Classifier: Topic :: Software Development :: Quality Assurance
Classifier: Topic :: Software Development :: Testing
Requires-Dist: beautifulsoup4
Requires-Dist: cssify
Requires-Dist: jinja2
Requires-Dist: litellm
Requires-Dist: lxml
Requires-Dist: opencv-python-headless
Requires-Dist: parsimonious
Requires-Dist: pyautogui
Requires-Dist: python-dotenv
Requires-Dist: robotframework
Requires-Dist: robotframework-appiumlibrary
Requires-Dist: robotframework-browser
Requires-Dist: robotframework-seleniumlibrary
Requires-Dist: thefuzz
Requires-Dist: tinydb
Project-URL: Homepage, https://github.com/hieuld/smart-selfhealing-rbfw
